setup.py
collective/__init__.py
collective.portlet.links.egg-info/PKG-INFO
collective.portlet.links.egg-info/SOURCES.txt
collective.portlet.links.egg-info/dependency_links.txt
collective.portlet.links.egg-info/entry_points.txt
collective.portlet.links.egg-info/namespace_packages.txt
collective.portlet.links.egg-info/not-zip-safe
collective.portlet.links.egg-info/requires.txt
collective.portlet.links.egg-info/top_level.txt
collective/portlet/__init__.py
collective/portlet/links/__init__.py
collective/portlet/links/configure.zcml
collective/portlet/links/linkportlet.pt
collective/portlet/links/linkportlet.py
collective/portlet/links/browser/__init__.py
collective/portlet/links/browser/configure.zcml
collective/portlet/links/browser/images/contents.txt
collective/portlet/links/browser/stylesheets/.main.css.swp
collective/portlet/links/browser/stylesheets/main.css
collective/portlet/links/profiles/default/portlets.xml
collective/portlet/links/profiles/default/stylesheets.xml
collective/portlet/links/tests/__init__.py
collective/portlet/links/tests/base.py
collective/portlet/links/tests/test_portlet.py