Metadata-Version: 1.0
Name: collective.portlet.links
Version: 0.2
Summary: A Plone portlet with configureable links.
Home-page: UNKNOWN
Author: Jan Filip Tristan Hasecke
Author-email: blenderkid@web.de
License: GPL
Platform: UNKNOWN
Classifier: Framework :: Plone
Classifier: Framework :: Zope2
Classifier: Framework :: Zope3
Classifier: Programming Language :: Python
Classifier: Topic :: Software Development :: Libraries :: Python Modules
